lk21/__init__.py
lk21/cli.py
lk21/options.py
lk21/utils.py
lk21/extractors/__init__.py
lk21/extractors/anibatch.py
lk21/extractors/anikyojin.py
lk21/extractors/animeindo.py
lk21/extractors/anitoki.py
lk21/extractors/bbcsjav.py
lk21/extractors/bypasser.py
lk21/extractors/dramaindo.py
lk21/extractors/drivenime.py
lk21/extractors/kdramaindo.py
lk21/extractors/kusonime.py
lk21/extractors/layarkaca21.py
lk21/extractors/melongmovie.py
lk21/extractors/meownime.py
lk21/extractors/nekopoi.py
lk21/extractors/oploverz.py
lk21/extractors/otakudesu.py
lk21/extractors/riie.py
lk21/extractors/samehadaku.py
lk21/extractors/wibudesu.py
lk21/extractors/zonawibu.py
lk21/thirdparty/__init__.py
lk21/thirdparty/exrex.py
lk21-1.6.0.dist-info/entry_points.txt
lk21-1.6.0.dist-info/LICENSE
lk21-1.6.0.dist-info/WHEEL
lk21-1.6.0.dist-info/METADATA
lk21-1.6.0.dist-info/RECORD
