Metadata-Version: 2.1
Name: lk21
Version: 1.6.0
Summary: unduh anime dan film subtitle Indonesia
Home-page: https://github.com/zevtyardt
License: MIT
Author: Val
Author-email: apklover76@gmail.com
Requires-Python: >=3.8
Classifier: License :: OSI Approved :: MIT License
Requires-Dist: questionary
Requires-Dist: bs4
Requires-Dist: requests
Requires-Dist: requests-cache
Requires-Dist: colorama
